ecc_analyzer/__init__.py
ecc_analyzer/system_base.py
ecc_analyzer/core/__init__.py
ecc_analyzer/core/asil_block.py
ecc_analyzer/core/base.py
ecc_analyzer/core/basic_event.py
ecc_analyzer/core/coverage_block.py
ecc_analyzer/core/observable_block.py
ecc_analyzer/core/pipeline_block.py
ecc_analyzer/core/split_block.py
ecc_analyzer/core/sum_block.py
ecc_analyzer/core/transformation_block.py
ecc_analyzer/interfaces/__init__.py
ecc_analyzer/interfaces/block_interface.py
ecc_analyzer/interfaces/fault_type.py
ecc_analyzer/interfaces/observable_interface.py
ecc_analyzer/interfaces/observer.py
ecc_analyzer/models/__init__.py
ecc_analyzer/models/lpddr4/__init__.py
ecc_analyzer/models/lpddr4/bus_trim.py
ecc_analyzer/models/lpddr4/dram_trim.py
ecc_analyzer/models/lpddr4/events.py
ecc_analyzer/models/lpddr4/lpddr4_system.py
ecc_analyzer/models/lpddr4/other_components.py
ecc_analyzer/models/lpddr4/sec.py
ecc_analyzer/models/lpddr4/sec_ded.py
ecc_analyzer/models/lpddr4/sec_ded_trim.py
ecc_analyzer/models/lpddr5/__init__.py
ecc_analyzer/models/lpddr5/bus_trim.py
ecc_analyzer/models/lpddr5/dram_trim.py
ecc_analyzer/models/lpddr5/events.py
ecc_analyzer/models/lpddr5/link_ecc.py
ecc_analyzer/models/lpddr5/lpddr5_system.py
ecc_analyzer/models/lpddr5/other_components.py
ecc_analyzer/models/lpddr5/sec.py
ecc_analyzer/models/lpddr5/sec_ded.py
ecc_analyzer/models/lpddr5/sec_ded_trim.py
ecc_analyzer/visualization/__init__.py
ecc_analyzer/visualization/safety_visualizer.py
iso26262_ecc_analyzer-0.1.0.dist-info/METADATA
iso26262_ecc_analyzer-0.1.0.dist-info/WHEEL
iso26262_ecc_analyzer-0.1.0.dist-info/top_level.txt
iso26262_ecc_analyzer-0.1.0.dist-info/RECORD
