Metadata-Version: 2.4
Name: iso26262-ecc-analyzer
Version: 0.1.0
Summary: Safety analysis and visualization tool according to ISO 26262.
Author-email: Linus Held <your.email@example.com>
License: MIT
Project-URL: Homepage, https://github.com/HENKI2004/iso26262-ecc-analyzer
Project-URL: Bug Tracker, https://github.com/HENKI2004/iso26262-ecc-analyzer/issues
Project-URL: Documentation, https://henki2004.github.io/iso26262-ecc-analyzer/
Requires-Python: >=3.9
Requires-Dist: graphviz>=0.20
Provides-Extra: dev
Requires-Dist: pytest; extra == "dev"
Requires-Dist: black; extra == "dev"
Requires-Dist: ruff; extra == "dev"
